dotnetAddDlls/__init__.py
dotnetAddDlls-0.1.data/data/templates/RefTemplate.xml
dotnetAddDlls-0.1.dist-info/METADATA
dotnetAddDlls-0.1.dist-info/RECORD
dotnetAddDlls-0.1.dist-info/WHEEL
dotnetAddDlls-0.1.dist-info/entry_points.txt
dotnetAddDlls-0.1.dist-info/top_level.txt
