Metadata-Version: 2.1
Name: dotnetAddDlls
Version: 0.1
Summary: Add dlls to your dotnet core project
Home-page: https://github.com/YotamShvartsun/dotnetAddDlls
Author: Yotam Shvartsun
Author-email: yotam.shvartsun@gmail.com
License: MIT
Platform: UNKNOWN
